{
  "items": [
      {
          "id": "tt6723592",
          "rank": "1",
          "rankUpDown": "0",
          "title": "Tenet",
          "fullTitle": "Tenet (2020)",
          "year": "2020",
          "image": "https://m.media-amazon.com/images/M/MV5BYzg0NGM2NjAtNmIxOC00MDJmLTg5ZmYtYzM0MTE4NWE2NzlhXkEyXkFqcGdeQXVyMTA4NjE0NjEy._V1_UX128_CR0,3,128,176_AL_.jpg",
          "crew": "Christopher Nolan (dir.), John David Washington, Robert Pattinson",
          "imDbRating": "7.6",
          "imDbRatingCount": "199097"
      },
      {
          "id": "tt10618286",
          "rank": "2",
          "rankUpDown": "+3",
          "title": "Mank",
          "fullTitle": "Mank (2020)",
          "year": "2020",
          "image": "https://m.media-amazon.com/images/M/MV5BZjAzNDE2YzMtM2E4OC00NWViLTkwZTItYmVmYmNkYWNhOTMwXkEyXkFqcGdeQXVyMTkxNjUyNQ@@._V1_UX128_CR0,3,128,176_AL_.jpg",
          "crew": "David Fincher (dir.), Gary Oldman, Amanda Seyfried",
          "imDbRating": "7.2",
          "imDbRatingCount": "20182"
      },
      {
          "id": "tt4566758",
          "rank": "3",
          "rankUpDown": "+7",
          "title": "Mulan",
          "fullTitle": "Mulan (2020)",
          "year": "2020",
          "image": "https://m.media-amazon.com/images/M/MV5BNDliY2E1MjUtNzZkOS00MzJlLTgyOGEtZDg4MTI1NzZkMTBhXkEyXkFqcGdeQXVyNjMwMzc3MjE@._V1_UX128_CR0,3,128,176_AL_.jpg",
          "crew": "Niki Caro (dir.), Yifei Liu, Donnie Yen",
          "imDbRating": "5.6",
          "imDbRatingCount": "84887"
      },
      {
          "id": "tt8784956",
          "rank": "4",
          "rankUpDown": "+77",
          "title": "Ava",
          "fullTitle": "Ava (2020)",
          "year": "2020",
          "image": "https://m.media-amazon.com/images/M/MV5BMTMzMTg1MjgtOWNhYy00NmZmLWExOTctMjA2OTZhZDFkNDhhXkEyXkFqcGdeQXVyNzAwMjU2MTY@._V1_UX128_CR0,3,128,176_AL_.jpg",
          "crew": "Tate Taylor (dir.), Jessica Chastain, John Malkovich",
          "imDbRating": "5.3",
          "imDbRatingCount": "25665"
      },
      {
          "id": "tt7126948",
          "rank": "5",
          "rankUpDown": "+11",
          "title": "Wonder Woman 1984",
          "fullTitle": "Wonder Woman 1984 (2020)",
          "year": "2020",
          "image": "https://m.media-amazon.com/images/M/MV5BNWY2NWE0NWEtZGUwMC00NWMwLTkyNzUtNmIxMmIyYzA0MjNiXkEyXkFqcGdeQXVyMTA2OTQ3MTUy._V1_UX128_CR0,3,128,176_AL_.jpg",
          "crew": "Patty Jenkins (dir.), Gal Gadot, Chris Pine",
          "imDbRating": "",
          "imDbRatingCount": "0"
      },
      {
          "id": "tt11681250",
          "rank": "6",
          "rankUpDown": "+19",
          "title": "Godmothered",
          "fullTitle": "Godmothered (2020)",
          "year": "2020",
          "image": "https://m.media-amazon.com/images/M/MV5BZTdkYjM0ZTQtNTc5NS00YzcxLWI0OTMtNTVjNmRlMGE3MmUzXkEyXkFqcGdeQXVyNjMwMzc3MjE@._V1_UX128_CR0,3,128,176_AL_.jpg",
          "crew": "Sharon Maguire (dir.), June Squibb, Jillian Bell",
          "imDbRating": "6.1",
          "imDbRatingCount": "4115"
      },
      {
          "id": "tt10161886",
          "rank": "7",
          "rankUpDown": "+31",
          "title": "The Prom",
          "fullTitle": "The Prom (2020)",
          "year": "2020",
          "image": "https://m.media-amazon.com/images/M/MV5BMjUyN2U3YjgtZmFjZC00MzBlLWFkZDItZWQxM2QwMDdjNDMyXkEyXkFqcGdeQXVyODE5NzE3OTE@._V1_UX128_CR0,3,128,176_AL_.jpg",
          "crew": "Ryan Murphy (dir.), Meryl Streep, James Corden",
          "imDbRating": "6.2",
          "imDbRatingCount": "7970"
      },
      {
          "id": "tt8522006",
          "rank": "8",
          "rankUpDown": "-6",
          "title": "Happiest Season",
          "fullTitle": "Happiest Season (2020)",
          "year": "2020",
          "image": "https://m.media-amazon.com/images/M/MV5BZDgyZDNiZGEtYmQ4NC00NzU5LTllODQtNjIwMGY2NDYyNGQwXkEyXkFqcGdeQXVyMTkxNjUyNQ@@._V1_UX128_CR0,3,128,176_AL_.jpg",
          "crew": "Clea DuVall (dir.), Kristen Stewart, Mackenzie Davis",
          "imDbRating": "6.7",
          "imDbRatingCount": "15730"
      },
      {
          "id": "tt0099785",
          "rank": "9",
          "rankUpDown": "0",
          "title": "Home Alone",
          "fullTitle": "Home Alone (1990)",
          "year": "1990",
          "image": "https://m.media-amazon.com/images/M/MV5BMzFkM2YwOTQtYzk2Mi00N2VlLWE3NTItN2YwNDg1YmY0ZDNmXkEyXkFqcGdeQXVyMTMxODk2OTU@._V1_UX128_CR0,3,128,176_AL_.jpg",
          "crew": "Chris Columbus (dir.), Macaulay Culkin, Joe Pesci",
          "imDbRating": "7.6",
          "imDbRatingCount": "466954"
      },
      {
          "id": "tt11057644",
          "rank": "10",
          "rankUpDown": "-6",
          "title": "The Christmas Chronicles: Part Two",
          "fullTitle": "The Christmas Chronicles: Part Two (2020)",
          "year": "2020",
          "image": "https://m.media-amazon.com/images/M/MV5BMGJiZDc1OWMtNzMwMC00NzM0LTljMDgtZGJjODVhZDMzMmJjXkEyXkFqcGdeQXVyODk4OTc3MTY@._V1_UX128_CR0,3,128,176_AL_.jpg",
          "crew": "Chris Columbus (dir.), Kurt Russell, Goldie Hawn",
          "imDbRating": "6.0",
          "imDbRatingCount": "11754"
      },
      {
          "id": "tt1838556",
          "rank": "11",
          "rankUpDown": "+166",
          "title": "Honest Thief",
          "fullTitle": "Honest Thief (2020)",
          "year": "2020",
          "image": "https://m.media-amazon.com/images/M/MV5BZjEwNjYyMTMtODc5Yi00NTg5LTkwMzAtZTkyOTcyNTFkMGIyXkEyXkFqcGdeQXVyMDA4NzMyOA@@._V1_UX128_CR0,3,128,176_AL_.jpg",
          "crew": "Mark Williams (dir.), Liam Neeson, Kate Walsh",
          "imDbRating": "6.0",
          "imDbRatingCount": "11147"
      },
      {
          "id": "tt0097958",
          "rank": "12",
          "rankUpDown": "+6",
          "title": "National Lampoon's Christmas Vacation",
          "fullTitle": "National Lampoon's Christmas Vacation (1989)",
          "year": "1989",
          "image": "https://m.media-amazon.com/images/M/MV5BMGZkMWQ2MzMtYTkxYS00OThmLWI0ZTQtNmY0ZTkyY2E4MjliXkEyXkFqcGdeQXVyMTQxNzMzNDI@._V1_UX128_CR0,3,128,176_AL_.jpg",
          "crew": "Jeremiah S. Chechik (dir.), Chevy Chase, Beverly D'Angelo",
          "imDbRating": "7.6",
          "imDbRatingCount": "152870"
      },
      {
          "id": "tt0314331",
          "rank": "13",
          "rankUpDown": "+18",
          "title": "Love Actually",
          "fullTitle": "Love Actually (2003)",
          "year": "2003",
          "image": "https://m.media-amazon.com/images/M/MV5BMTY4NjQ5NDc0Nl5BMl5BanBnXkFtZTYwNjk5NDM3._V1_UX128_CR0,3,128,176_AL_.jpg",
          "crew": "Richard Curtis (dir.), Hugh Grant, Martine McCutcheon",
          "imDbRating": "7.6",
          "imDbRatingCount": "423403"
      },
      {
          "id": "tt10919380",
          "rank": "14",
          "rankUpDown": "0",
          "title": "Freaky",
          "fullTitle": "Freaky (2020)",
          "year": "2020",
          "image": "https://m.media-amazon.com/images/M/MV5BMTRkYmJlY2ItNmFlZi00OWVhLTg1ZTctOGE0MjM5ZGMwMmY4XkEyXkFqcGdeQXVyNjY1MTg4Mzc@._V1_UX128_CR0,3,128,176_AL_.jpg",
          "crew": "Christopher Landon (dir.), Vince Vaughn, Kathryn Newton",
          "imDbRating": "6.4",
          "imDbRatingCount": "12015"
      },
      {
          "id": "tt0319343",
          "rank": "15",
          "rankUpDown": "+2",
          "title": "Elf",
          "fullTitle": "Elf (2003)",
          "year": "2003",
          "image": "https://m.media-amazon.com/images/M/MV5BMzUxNzkzMzQtYjIxZC00NzU0LThkYTQtZjNhNTljMTA1MDA1L2ltYWdlL2ltYWdlXkEyXkFqcGdeQXVyMTMxODk2OTU@._V1_UX128_CR0,3,128,176_AL_.jpg",
          "crew": "Jon Favreau (dir.), Will Ferrell, James Caan",
          "imDbRating": "7.0",
          "imDbRatingCount": "219102"
      },
      {
          "id": "tt6772802",
          "rank": "16",
          "rankUpDown": "-13",
          "title": "Hillbilly Elegy",
          "fullTitle": "Hillbilly Elegy (2020)",
          "year": "2020",
          "image": "https://m.media-amazon.com/images/M/MV5BZGI4NzRkNDgtYzQyOS00YWVjLTllYzctNmQ5NzkzOGIxMDBhXkEyXkFqcGdeQXVyODE5NzE3OTE@._V1_UX128_CR0,3,128,176_AL_.jpg",
          "crew": "Ron Howard (dir.), Amy Adams, Glenn Close",
          "imDbRating": "6.7",
          "imDbRatingCount": "15153"
      },
      {
          "id": "tt0170016",
          "rank": "17",
          "rankUpDown": "+4",
          "title": "How the Grinch Stole Christmas",
          "fullTitle": "How the Grinch Stole Christmas (2000)",
          "year": "2000",
          "image": "https://m.media-amazon.com/images/M/MV5BNWNiNTczNzEtMjQyZC00MjFmLTkzMDMtODk4ZGMyZmE0N2E4XkEyXkFqcGdeQXVyMTMxODk2OTU@._V1_UX128_CR0,3,128,176_AL_.jpg",
          "crew": "Ron Howard (dir.), Jim Carrey, Taylor Momsen",
          "imDbRating": "6.2",
          "imDbRatingCount": "205547"
      },
      {
          "id": "tt5363618",
          "rank": "18",
          "rankUpDown": "+37",
          "title": "Sound of Metal",
          "fullTitle": "Sound of Metal (2019)",
          "year": "2019",
          "image": "https://m.media-amazon.com/images/M/MV5BNjcyYjg0M2ItMzMyZS00NmM1LTlhZDMtN2MxN2RhNWY4YTkwXkEyXkFqcGdeQXVyNjY1MTg4Mzc@._V1_UX128_CR0,3,128,176_AL_.jpg",
          "crew": "Darius Marder (dir.), Riz Ahmed, Olivia Cooke",
          "imDbRating": "7.8",
          "imDbRatingCount": "6935"
      },
      {
          "id": "tt10539608",
          "rank": "19",
          "rankUpDown": "+63",
          "title": "The Midnight Sky",
          "fullTitle": "The Midnight Sky (2020)",
          "year": "2020",
          "image": "https://m.media-amazon.com/images/M/MV5BNDQwYjJjODMtOWNmNC00NDJjLThiNDgtNzVkOTM1MjY5NDQ5XkEyXkFqcGdeQXVyMTEyMjM2NDc2._V1_UX128_CR0,3,128,176_AL_.jpg",
          "crew": "George Clooney (dir.), George Clooney, Felicity Jones",
          "imDbRating": "5.2",
          "imDbRatingCount": "314"
      },
      {
          "id": "tt7737786",
          "rank": "20",
          "rankUpDown": "+3",
          "title": "Greenland",
          "fullTitle": "Greenland (2020)",
          "year": "2020",
          "image": "https://m.media-amazon.com/images/M/MV5BMzcyMzU4MDUtM2JhOC00ZDg2LTg5MGMtZjc2OGMyMjhlMGE2XkEyXkFqcGdeQXVyMTkxNjUyNQ@@._V1_UX128_CR0,3,128,176_AL_.jpg",
          "crew": "Ric Roman Waugh (dir.), Gerard Butler, Morena Baccarin",
          "imDbRating": "6.3",
          "imDbRatingCount": "30247"
      },
      {
          "id": "tt2990140",
          "rank": "21",
          "rankUpDown": "-14",
          "title": "The Christmas Chronicles",
          "fullTitle": "The Christmas Chronicles (2018)",
          "year": "2018",
          "image": "https://m.media-amazon.com/images/M/MV5BNTA3NjU3OTM2MV5BMl5BanBnXkFtZTgwNjQ2MzE1NjM@._V1_UX128_CR0,3,128,176_AL_.jpg",
          "crew": "Clay Kaytis (dir.), Kurt Russell, Darby Camp",
          "imDbRating": "7.1",
          "imDbRatingCount": "52267"
      },
      {
          "id": "tt7736496",
          "rank": "22",
          "rankUpDown": "-7",
          "title": "Jingle Jangle: A Christmas Journey",
          "fullTitle": "Jingle Jangle: A Christmas Journey (2020)",
          "year": "2020",
          "image": "https://m.media-amazon.com/images/M/MV5BMjU1MGEzMTUtNjg4ZC00MjgzLTkxODYtZGU4MGJkMDU0NzA4XkEyXkFqcGdeQXVyNTE1NjY5Mg@@._V1_UX128_CR0,3,128,176_AL_.jpg",
          "crew": "David E. Talbert (dir.), Forest Whitaker, Keegan-Michael Key",
          "imDbRating": "6.5",
          "imDbRatingCount": "9474"
      },
      {
          "id": "tt10310140",
          "rank": "23",
          "rankUpDown": "-3",
          "title": "Fatman",
          "fullTitle": "Fatman (2020)",
          "year": "2020",
          "image": "https://m.media-amazon.com/images/M/MV5BZjk1NDc4OTEtY2M3OS00M2E3LTk4YTgtYjczMzI1OWQ1ODVlXkEyXkFqcGdeQXVyNzA0OTM3NQ@@._V1_UX128_CR0,3,128,176_AL_.jpg",
          "crew": "Eshom Nelms (dir.), Mel Gibson, Walton Goggins",
          "imDbRating": "5.9",
          "imDbRatingCount": "8965"
      },
      {
          "id": "tt0111070",
          "rank": "24",
          "rankUpDown": "+12",
          "title": "The Santa Clause",
          "fullTitle": "The Santa Clause (1994)",
          "year": "1994",
          "image": "https://m.media-amazon.com/images/M/MV5BMTZlNzk1MjItYjJlYy00MTAxLWJkNjEtZmNiNmVlNjQ4NDE5XkEyXkFqcGdeQXVyMzI0NDc4ODY@._V1_UX128_CR0,3,128,176_AL_.jpg",
          "crew": "John Pasquin (dir.), Tim Allen, Judge Reinhold",
          "imDbRating": "6.5",
          "imDbRatingCount": "95869"
      },
      {
          "id": "tt2709692",
          "rank": "25",
          "rankUpDown": "+12",
          "title": "The Grinch",
          "fullTitle": "The Grinch (2018)",
          "year": "2018",
          "image": "https://m.media-amazon.com/images/M/MV5BYmE5Yjg0MzktYzgzMi00YTFiLWJjYTItY2M5MmI1ODI4MDY3XkEyXkFqcGdeQXVyMTMxODk2OTU@._V1_UX128_CR0,3,128,176_AL_.jpg",
          "crew": "Yarrow Cheney (dir.), Benedict Cumberbatch, Cameron Seely",
          "imDbRating": "6.3",
          "imDbRatingCount": "49803"
      },
      {
          "id": "tt10600398",
          "rank": "26",
          "rankUpDown": "+97",
          "title": "We Can Be Heroes",
          "fullTitle": "We Can Be Heroes (2020)",
          "year": "2020",
          "image": "https://m.media-amazon.com/images/M/MV5BYmU3OGFhZDItMjhlZi00YjQwLWJlOTItYzlhOGEwNGU3NjIwXkEyXkFqcGdeQXVyMTkxNjUyNQ@@._V1_UX128_CR0,3,128,176_AL_.jpg",
          "crew": "Robert Rodriguez (dir.), Pedro Pascal, Taylor Dooley",
          "imDbRating": "",
          "imDbRatingCount": "0"
      },
      {
          "id": "tt10872600",
          "rank": "27",
          "rankUpDown": "+595",
          "title": "Untitled Spider-Man Sequel",
          "fullTitle": "Untitled Spider-Man Sequel (2021)",
          "year": "2021",
          "image": "https://imdb-api.com/images/128x176/nopicture.jpg",
          "crew": "Jon Watts (dir.), Tom Holland, Zendaya",
          "imDbRating": "",
          "imDbRatingCount": "0"
      },
      {
          "id": "tt0033467",
          "rank": "28",
          "rankUpDown": "+40",
          "title": "Citizen Kane",
          "fullTitle": "Citizen Kane (1941)",
          "year": "1941",
          "image": "https://m.media-amazon.com/images/M/MV5BYjBiOTYxZWItMzdiZi00NjlkLWIzZTYtYmFhZjhiMTljOTdkXkEyXkFqcGdeQXVyNzkwMjQ5NzM@._V1_UX128_CR0,3,128,176_AL_.jpg",
          "crew": "Orson Welles (dir.), Orson Welles, Joseph Cotten",
          "imDbRating": "8.3",
          "imDbRatingCount": "398210"
      },
      {
          "id": "tt9689696",
          "rank": "29",
          "rankUpDown": "+17",
          "title": "Wander",
          "fullTitle": "Wander (2020)",
          "year": "2020",
          "image": "https://m.media-amazon.com/images/M/MV5BMTM5MjI5N2YtNTRjOS00Mzk1LTlmODAtZTJmZjQ5NzNhODNkXkEyXkFqcGdeQXVyNTIwMDQ0NA@@._V1_UX128_CR0,3,128,176_AL_.jpg",
          "crew": "April Mullen (dir.), Aaron Eckhart, Tommy Lee Jones",
          "imDbRating": "5.0",
          "imDbRatingCount": "1757"
      },
      {
          "id": "tt0095016",
          "rank": "30",
          "rankUpDown": "+24",
          "title": "Die Hard",
          "fullTitle": "Die Hard (1988)",
          "year": "1988",
          "image": "https://m.media-amazon.com/images/M/MV5BZjRlNDUxZjAtOGQ4OC00OTNlLTgxNmQtYTBmMDgwZmNmNjkxXkEyXkFqcGdeQXVyNzkwMjQ5NzM@._V1_UX128_CR0,3,128,176_AL_.jpg",
          "crew": "John McTiernan (dir.), Bruce Willis, Alan Rickman",
          "imDbRating": "8.2",
          "imDbRatingCount": "778819"
      },
      {
          "id": "tt9866072",
          "rank": "31",
          "rankUpDown": "-7",
          "title": "Holidate",
          "fullTitle": "Holidate (2020)",
          "year": "2020",
          "image": "https://m.media-amazon.com/images/M/MV5BYWVmYTFjODItOTY2Ni00NDhhLTk1ZDYtMzBmOGFhZTMyY2Q0XkEyXkFqcGdeQXVyMTEyMjM2NDc2._V1_UX128_CR0,3,128,176_AL_.jpg",
          "crew": "John Whitesell (dir.), Emma Roberts, Luke Bracey",
          "imDbRating": "6.1",
          "imDbRatingCount": "33736"
      },
      {
          "id": "tt9601220",
          "rank": "32",
          "rankUpDown": "+20",
          "title": "Black Bear",
          "fullTitle": "Black Bear (2020)",
          "year": "2020",
          "image": "https://m.media-amazon.com/images/M/MV5BYTE0ZGVkNzctNTE1Ny00NGM2LWIzYzUtMDQ1YzAyYmQyYTE3XkEyXkFqcGdeQXVyMTAyMjQ3NzQ1._V1_UX128_CR0,3,128,176_AL_.jpg",
          "crew": "Lawrence Michael Levine (dir.), Aubrey Plaza, Sarah Gadon",
          "imDbRating": "6.5",
          "imDbRatingCount": "2221"
      },
      {
          "id": "tt8623904",
          "rank": "33",
          "rankUpDown": "-7",
          "title": "Last Christmas",
          "fullTitle": "Last Christmas (2019)",
          "year": "2019",
          "image": "https://m.media-amazon.com/images/M/MV5BNTQ4ZmY0NjgtYzVhNy00NzhiLTk3YTYtNzM1MTdjM2VhZDA3XkEyXkFqcGdeQXVyMTkxNjUyNQ@@._V1_UX128_CR0,3,128,176_AL_.jpg",
          "crew": "Paul Feig (dir.), Madison Ingoldsby, Emma Thompson",
          "imDbRating": "6.5",
          "imDbRatingCount": "46804"
      },
      {
          "id": "tt8633478",
          "rank": "34",
          "rankUpDown": "-12",
          "title": "Run",
          "fullTitle": "Run (2020)",
          "year": "2020",
          "image": "https://m.media-amazon.com/images/M/MV5BMDcwOWVkZTEtNjJhMy00MGI0LWI3NmYtOGY5NWYxZTQ0YTE5XkEyXkFqcGdeQXVyMjkwOTAyMDU@._V1_UX128_CR0,3,128,176_AL_.jpg",
          "crew": "Aneesh Chaganty (dir.), Sarah Paulson, Kiera Allen",
          "imDbRating": "6.7",
          "imDbRatingCount": "15086"
      },
      {
          "id": "tt6475714",
          "rank": "35",
          "rankUpDown": "+80",
          "title": "Monster Hunter",
          "fullTitle": "Monster Hunter (2020)",
          "year": "2020",
          "image": "https://m.media-amazon.com/images/M/MV5BOGU3NTFmNjYtODc3Ny00MWEzLWI3M2ItZjE3NDgwMTI0MzkzXkEyXkFqcGdeQXVyMTEyMjM2NDc2._V1_UX128_CR0,3,128,176_AL_.jpg",
          "crew": "Paul W.S. Anderson (dir.), Milla Jovovich, Tony Jaa",
          "imDbRating": "5.3",
          "imDbRatingCount": "1043"
      },
      {
          "id": "tt0104431",
          "rank": "36",
          "rankUpDown": "+17",
          "title": "Home Alone 2: Lost in New York",
          "fullTitle": "Home Alone 2: Lost in New York (1992)",
          "year": "1992",
          "image": "https://m.media-amazon.com/images/M/MV5BNDI1MzM0Y2YtYmIyMS00ODE3LTlhZjEtZTUyNmEzMTNhZWU5XkEyXkFqcGdeQXVyMTQxNzMzNDI@._V1_UX128_CR0,3,128,176_AL_.jpg",
          "crew": "Chris Columbus (dir.), Macaulay Culkin, Joe Pesci",
          "imDbRating": "6.8",
          "imDbRatingCount": "299314"
      },
      {
          "id": "tt10808832",
          "rank": "37",
          "rankUpDown": "+386",
          "title": "Let Them All Talk",
          "fullTitle": "Let Them All Talk (2020)",
          "year": "2020",
          "image": "https://m.media-amazon.com/images/M/MV5BOWIwMDFiZTMtMTc2NS00ZjkxLWJmNDgtOWFhZjVkNDNkZTgzXkEyXkFqcGdeQXVyMTEyMjM2NDc2._V1_UX128_CR0,3,128,176_AL_.jpg",
          "crew": "Steven Soderbergh (dir.), Meryl Streep, Gemma Chan",
          "imDbRating": "6.1",
          "imDbRatingCount": "1802"
      },
      {
          "id": "tt8333746",
          "rank": "38",
          "rankUpDown": "1,505",
          "title": "Pinocchio",
          "fullTitle": "Pinocchio (2019)",
          "year": "2019",
          "image": "https://m.media-amazon.com/images/M/MV5BNzgxNWJiOWQtZDA5Mi00NjBkLWIxMzUtZTg3Yjk5NjYyMDZjXkEyXkFqcGdeQXVyMDA4NzMyOA@@._V1_UX128_CR0,3,128,176_AL_.jpg",
          "crew": "Matteo Garrone (dir.), Federico Ielapi, Roberto Benigni",
          "imDbRating": "6.2",
          "imDbRatingCount": "5690"
      },
      {
          "id": "tt6850820",
          "rank": "39",
          "rankUpDown": "+36",
          "title": "Peppermint",
          "fullTitle": "Peppermint (2018)",
          "year": "2018",
          "image": "https://m.media-amazon.com/images/M/MV5BNWVlMjQ3MjItOWE3YS00YTYwLWE0ZDMtZWMyZWY1NzkxNWIwXkEyXkFqcGdeQXVyMTMxODk2OTU@._V1_UX128_CR0,3,128,176_AL_.jpg",
          "crew": "Pierre Morel (dir.), Jennifer Garner, John Gallagher Jr.",
          "imDbRating": "6.5",
          "imDbRatingCount": "53492"
      },
      {
          "id": "tt4729430",
          "rank": "40",
          "rankUpDown": "+21",
          "title": "Klaus",
          "fullTitle": "Klaus (2019)",
          "year": "2019",
          "image": "https://m.media-amazon.com/images/M/MV5BMWYwOThjM2ItZGYxNy00NTQwLWFlZWEtM2MzM2Q5MmY3NDU5XkEyXkFqcGdeQXVyMTkxNjUyNQ@@._V1_UX128_CR0,3,128,176_AL_.jpg",
          "crew": "Sergio Pablos (dir.), Jason Schwartzman, J.K. Simmons",
          "imDbRating": "8.2",
          "imDbRatingCount": "85679"
      },
      {
          "id": "tt10530176",
          "rank": "41",
          "rankUpDown": "-22",
          "title": "The Call",
          "fullTitle": "The Call (2020)",
          "year": "2020",
          "image": "https://m.media-amazon.com/images/M/MV5BMjlhYzY4ODQtYWY3ZS00NGUwLTk5NWYtYjBlMjUzMmNkZWU0XkEyXkFqcGdeQXVyMTA5NzUzODM4._V1_UX128_CR0,1,128,176_AL_.jpg",
          "crew": "Chung-Hyun Lee (dir.), Park Shin-Hye, Jong-seo Jun",
          "imDbRating": "7.1",
          "imDbRatingCount": "8589"
      },
      {
          "id": "tt0038650",
          "rank": "42",
          "rankUpDown": "+65",
          "title": "It's a Wonderful Life",
          "fullTitle": "It's a Wonderful Life (1946)",
          "year": "1946",
          "image": "https://m.media-amazon.com/images/M/MV5BZjc4NDZhZWMtNGEzYS00ZWU2LThlM2ItNTA0YzQ0OTExMTE2XkEyXkFqcGdeQXVyNjUwMzI2NzU@._V1_UX128_CR0,3,128,176_AL_.jpg",
          "crew": "Frank Capra (dir.), James Stewart, Donna Reed",
          "imDbRating": "8.6",
          "imDbRatingCount": "394975"
      },
      {
          "id": "tt6902332",
          "rank": "43",
          "rankUpDown": "+214",
          "title": "The Marksman",
          "fullTitle": "The Marksman (2021)",
          "year": "2021",
          "image": "https://m.media-amazon.com/images/M/MV5BMDE2ZjU4ZjgtOTI5Mi00ZWMwLTlkYjMtZWU1NTVjNjRhOWJiXkEyXkFqcGdeQXVyMTkxNjUyNQ@@._V1_UX128_CR0,1,128,176_AL_.jpg",
          "crew": "Robert Lorenz (dir.), Katheryn Winnick, Liam Neeson",
          "imDbRating": "",
          "imDbRatingCount": "0"
      },
      {
          "id": "tt8367814",
          "rank": "44",
          "rankUpDown": "-1",
          "title": "The Gentlemen",
          "fullTitle": "The Gentlemen (2019)",
          "year": "2019",
          "image": "https://m.media-amazon.com/images/M/MV5BMTlkMmVmYjktYTc2NC00ZGZjLWEyOWUtMjc2MDMwMjQwOTA5XkEyXkFqcGdeQXVyNTI4MzE4MDU@._V1_UX128_CR0,3,128,176_AL_.jpg",
          "crew": "Guy Ritchie (dir.), Matthew McConaughey, Charlie Hunnam",
          "imDbRating": "7.8",
          "imDbRatingCount": "214745"
      },
      {
          "id": "tt9214832",
          "rank": "45",
          "rankUpDown": "+13",
          "title": "Emma.",
          "fullTitle": "Emma. (2020)",
          "year": "2020",
          "image": "https://m.media-amazon.com/images/M/MV5BOGRiODEzM2QtOTUyYi00MWRlLTg4MzMtZGI0YmUzNWUyMjQ0XkEyXkFqcGdeQXVyMDA4NzMyOA@@._V1_UX128_CR0,3,128,176_AL_.jpg",
          "crew": "Autumn de Wilde (dir.), Anya Taylor-Joy, Johnny Flynn",
          "imDbRating": "6.7",
          "imDbRatingCount": "25797"
      },
      {
          "id": "tt1160419",
          "rank": "46",
          "rankUpDown": "-6",
          "title": "Dune",
          "fullTitle": "Dune (2021)",
          "year": "2021",
          "image": "https://m.media-amazon.com/images/M/MV5BMGFkZGY0NTgtMGEyZC00YzhjLTkyOWItYzMzOTljMDA3ZjU2XkEyXkFqcGdeQXVyNzc4NTU3Njg@._V1_UX128_CR0,3,128,176_AL_.jpg",
          "crew": "Denis Villeneuve (dir.), Zendaya, Timothée Chalamet",
          "imDbRating": "",
          "imDbRatingCount": "0"
      },
      {
          "id": "tt11327514",
          "rank": "47",
          "rankUpDown": "-35",
          "title": "Uncle Frank",
          "fullTitle": "Uncle Frank (2020)",
          "year": "2020",
          "image": "https://m.media-amazon.com/images/M/MV5BYWRkMzE5MDAtMTNjNS00ZmRhLWEyZTYtMTQyMGQ4NmFjNTU0XkEyXkFqcGdeQXVyNjY1MTg4Mzc@._V1_UX128_CR0,3,128,176_AL_.jpg",
          "crew": "Alan Ball (dir.), Paul Bettany, Sophia Lillis",
          "imDbRating": "7.2",
          "imDbRatingCount": "6119"
      },
      {
          "id": "tt0338348",
          "rank": "48",
          "rankUpDown": "+31",
          "title": "The Polar Express",
          "fullTitle": "The Polar Express (2004)",
          "year": "2004",
          "image": "https://m.media-amazon.com/images/M/MV5BMTM1NTU0NTE4MV5BMl5BanBnXkFtZTcwMTQ0MjEzMw@@._V1_UX128_CR0,3,128,176_AL_.jpg",
          "crew": "Robert Zemeckis (dir.), Tom Hanks, Chris Coppola",
          "imDbRating": "6.6",
          "imDbRatingCount": "172764"
      },
      {
          "id": "tt6394270",
          "rank": "49",
          "rankUpDown": "-17",
          "title": "Bombshell",
          "fullTitle": "Bombshell (2019)",
          "year": "2019",
          "image": "https://m.media-amazon.com/images/M/MV5BZjlhOWE3YjktY2MzOC00ZmQ1LWIwNjgtZmVhZmFjZGExMzgyXkEyXkFqcGdeQXVyMDA4NzMyOA@@._V1_UX128_CR0,3,128,176_AL_.jpg",
          "crew": "Jay Roach (dir.), Charlize Theron, Nicole Kidman",
          "imDbRating": "6.8",
          "imDbRatingCount": "82681"
      },
      {
          "id": "tt8946378",
          "rank": "50",
          "rankUpDown": "0",
          "title": "Knives Out",
          "fullTitle": "Knives Out (2019)",
          "year": "2019",
          "image": "https://m.media-amazon.com/images/M/MV5BMGUwZjliMTAtNzAxZi00MWNiLWE2NzgtZGUxMGQxZjhhNDRiXkEyXkFqcGdeQXVyNjU1NzU3MzE@._V1_UX128_CR0,3,128,176_AL_.jpg",
          "crew": "Rian Johnson (dir.), Daniel Craig, Chris Evans",
          "imDbRating": "7.9",
          "imDbRatingCount": "427398"
      },
      {
          "id": "tt11697484",
          "rank": "51",
          "rankUpDown": "-2",
          "title": "The 2nd",
          "fullTitle": "The 2nd (2020)",
          "year": "2020",
          "image": "https://m.media-amazon.com/images/M/MV5BY2M0Yzc5ODUtMThkZS00MmZmLWIzYjItOTAxYzJjZjMzODQ0XkEyXkFqcGdeQXVyMDM2NDM2MQ@@._V1_UX128_CR0,3,128,176_AL_.jpg",
          "crew": "Brian Skiba (dir.), Ryan Phillippe, Casper Van Dien",
          "imDbRating": "4.4",
          "imDbRatingCount": "3832"
      },
      {
          "id": "tt10886166",
          "rank": "52",
          "rankUpDown": "-10",
          "title": "365 Days",
          "fullTitle": "365 Days (2020)",
          "year": "2020",
          "image": "https://m.media-amazon.com/images/M/MV5BODljZTM3ODAtMDc0YS00NmI4LTlmZTUtM2I5MDAzNTQxZmMxXkEyXkFqcGdeQXVyMTEwMTY3NDI@._V1_UX128_CR0,1,128,176_AL_.jpg",
          "crew": "Barbara Bialowas (dir.), Anna Maria Sieklucka, Michele Morrone",
          "imDbRating": "3.3",
          "imDbRatingCount": "45631"
      },
      {
          "id": "tt10362466",
          "rank": "53",
          "rankUpDown": "-23",
          "title": "After We Collided",
          "fullTitle": "After We Collided (2020)",
          "year": "2020",
          "image": "https://m.media-amazon.com/images/M/MV5BN2UyNGM3MDUtMTIzZi00ZDdkLThlYTktYjk0ZDMzM2JiMjMyXkEyXkFqcGdeQXVyNzE0MjkxMzA@._V1_UX128_CR0,3,128,176_AL_.jpg",
          "crew": "Roger Kumble (dir.), Josephine Langford, Hero Fiennes Tiffin",
          "imDbRating": "5.0",
          "imDbRatingCount": "12671"
      },
      {
          "id": "tt4682266",
          "rank": "54",
          "rankUpDown": "-20",
          "title": "The New Mutants",
          "fullTitle": "The New Mutants (2020)",
          "year": "2020",
          "image": "https://m.media-amazon.com/images/M/MV5BZDQ2NTdmNDgtMGIwMS00ODE2LTk5M2EtZGZhYzc4MWRlNTU3XkEyXkFqcGdeQXVyNTc4MjczMTM@._V1_UX128_CR0,3,128,176_AL_.jpg",
          "crew": "Josh Boone (dir.), Maisie Williams, Anya Taylor-Joy",
          "imDbRating": "5.3",
          "imDbRatingCount": "34080"
      },
      {
          "id": "tt0068646",
          "rank": "55",
          "rankUpDown": "+11",
          "title": "The Godfather",
          "fullTitle": "The Godfather (1972)",
          "year": "1972",
          "image": "https://m.media-amazon.com/images/M/MV5BM2MyNjYxNmUtYTAwNi00MTYxLWJmNWYtYzZlODY3ZTk3OTFlXkEyXkFqcGdeQXVyNzkwMjQ5NzM@._V1_UX128_CR0,1,128,176_AL_.jpg",
          "crew": "Francis Ford Coppola (dir.), Marlon Brando, Al Pacino",
          "imDbRating": "9.2",
          "imDbRatingCount": "1600674"
      },
      {
          "id": "tt0096061",
          "rank": "56",
          "rankUpDown": "+46",
          "title": "Scrooged",
          "fullTitle": "Scrooged (1988)",
          "year": "1988",
          "image": "https://m.media-amazon.com/images/M/MV5BM2NlMDQzMDktNTMyZS00MjBjLWI0MmEtMzgzZDM2ZTVkNzE1XkEyXkFqcGdeQXVyNTUyMzE4Mzg@._V1_UX128_CR0,3,128,176_AL_.jpg",
          "crew": "Richard Donner (dir.), Bill Murray, Karen Allen",
          "imDbRating": "7.0",
          "imDbRatingCount": "85060"
      },
      {
          "id": "tt9264728",
          "rank": "57",
          "rankUpDown": "1,119",
          "title": "What Lies Below",
          "fullTitle": "What Lies Below (2020)",
          "year": "2020",
          "image": "https://m.media-amazon.com/images/M/MV5BOGQ4ZWM4NjctZDcwMS00OTJjLTljNmUtYWY4ODU3MjlkOGViXkEyXkFqcGdeQXVyODk4OTc3MTY@._V1_UX128_CR0,3,128,176_AL_.jpg",
          "crew": "Braden R. Duemmler (dir.), Ema Horvath, Troy Iwata",
          "imDbRating": "4.5",
          "imDbRatingCount": "826"
      },
      {
          "id": "tt7983894",
          "rank": "58",
          "rankUpDown": "+20",
          "title": "Ammonite",
          "fullTitle": "Ammonite (2020)",
          "year": "2020",
          "image": "https://m.media-amazon.com/images/M/MV5BZmM3ZGZlMWUtMjY1OS00NjBkLWE4MjQtODJkMmQ1MzdjYzhkXkEyXkFqcGdeQXVyMTkxNjUyNQ@@._V1_UX128_CR0,3,128,176_AL_.jpg",
          "crew": "Francis Lee (dir.), Kate Winslet, Saoirse Ronan",
          "imDbRating": "6.4",
          "imDbRatingCount": "2969"
      },
      {
          "id": "tt0304669",
          "rank": "59",
          "rankUpDown": "+26",
          "title": "The Santa Clause 2",
          "fullTitle": "The Santa Clause 2 (2002)",
          "year": "2002",
          "image": "https://m.media-amazon.com/images/M/MV5BNjU0Njk5MTA2Nl5BMl5BanBnXkFtZTYwODkzMzQ3._V1_UX128_CR0,3,128,176_AL_.jpg",
          "crew": "Michael Lembeck (dir.), Tim Allen, Spencer Breslin",
          "imDbRating": "5.6",
          "imDbRatingCount": "49737"
      },
      {
          "id": "tt6673612",
          "rank": "60",
          "rankUpDown": "+34",
          "title": "Dolittle",
          "fullTitle": "Dolittle (2020)",
          "year": "2020",
          "image": "https://m.media-amazon.com/images/M/MV5BMDNkODA5ZGQtODczOS00OTQxLThhMTItMjk0ZmNhMDM0YjNmXkEyXkFqcGdeQXVyMDM2NDM2MQ@@._V1_UX128_CR0,3,128,176_AL_.jpg",
          "crew": "Stephen Gaghan (dir.), Robert Downey Jr., Antonio Banderas",
          "imDbRating": "5.6",
          "imDbRatingCount": "44448"
      },
      {
          "id": "tt0120094",
          "rank": "61",
          "rankUpDown": "+388",
          "title": "Selena",
          "fullTitle": "Selena (1997)",
          "year": "1997",
          "image": "https://m.media-amazon.com/images/M/MV5BZGE0Y2RlNmQtZDY0Ni00Njk5LWFiZWUtMzc5N2VlZTBhOGE5L2ltYWdlL2ltYWdlXkEyXkFqcGdeQXVyMTQxNzMzNDI@._V1_UX128_CR0,3,128,176_AL_.jpg",
          "crew": "Gregory Nava (dir.), Jennifer Lopez, Edward James Olmos",
          "imDbRating": "6.8",
          "imDbRatingCount": "24888"
      },
      {
          "id": "tt0047673",
          "rank": "62",
          "rankUpDown": "+30",
          "title": "White Christmas",
          "fullTitle": "White Christmas (1954)",
          "year": "1954",
          "image": "https://m.media-amazon.com/images/M/MV5BYjI0ZTk0ZjQtZTMzOS00NDdmLTk0YzUtZTQ4NGRkNWFhZTkxXkEyXkFqcGdeQXVyNjc1NTYyMjg@._V1_UX128_CR0,3,128,176_AL_.jpg",
          "crew": "Michael Curtiz (dir.), Bing Crosby, Danny Kaye",
          "imDbRating": "7.6",
          "imDbRatingCount": "32298"
      },
      {
          "id": "tt0099674",
          "rank": "63",
          "rankUpDown": "+62",
          "title": "The Godfather: Part III",
          "fullTitle": "The Godfather: Part III (1990)",
          "year": "1990",
          "image": "https://m.media-amazon.com/images/M/MV5BNWFlYWY2YjYtNjdhNi00MzVlLTg2MTMtMWExNzg4NmM5NmEzXkEyXkFqcGdeQXVyMDk5Mzc5MQ@@._V1_UX128_CR0,3,128,176_AL_.jpg",
          "crew": "Francis Ford Coppola (dir.), Al Pacino, Diane Keaton",
          "imDbRating": "7.6",
          "imDbRatingCount": "355838"
      },
      {
          "id": "tt0457939",
          "rank": "64",
          "rankUpDown": "+29",
          "title": "The Holiday",
          "fullTitle": "The Holiday (2006)",
          "year": "2006",
          "image": "https://m.media-amazon.com/images/M/MV5BMTI1MDk4MzA2OF5BMl5BanBnXkFtZTYwMjQ3NDc3._V1_UX128_CR0,3,128,176_AL_.jpg",
          "crew": "Nancy Meyers (dir.), Kate Winslet, Cameron Diaz",
          "imDbRating": "6.9",
          "imDbRatingCount": "243475"
      },
      {
          "id": "tt8579674",
          "rank": "65",
          "rankUpDown": "-21",
          "title": "1917",
          "fullTitle": "1917 (2019)",
          "year": "2019",
          "image": "https://m.media-amazon.com/images/M/MV5BOTdmNTFjNDEtNzg0My00ZjkxLTg1ZDAtZTdkMDc2ZmFiNWQ1XkEyXkFqcGdeQXVyNTAzNzgwNTg@._V1_UX128_CR0,3,128,176_AL_.jpg",
          "crew": "Sam Mendes (dir.), Dean-Charles Chapman, George MacKay",
          "imDbRating": "8.3",
          "imDbRatingCount": "401015"
      },
      {
          "id": "tt7638348",
          "rank": "66",
          "rankUpDown": "-33",
          "title": "Boss Level",
          "fullTitle": "Boss Level (2021)",
          "year": "2021",
          "image": "https://m.media-amazon.com/images/M/MV5BMjlkZTJjMDQtMzI1My00YmViLWE0M2ItZTEwMzk1NDhlNDkwXkEyXkFqcGdeQXVyMzgxODI0MTk@._V1_UX128_CR0,3,128,176_AL_.jpg",
          "crew": "Joe Carnahan (dir.), Mel Gibson, Michelle Yeoh",
          "imDbRating": "",
          "imDbRatingCount": "0"
      },
      {
          "id": "tt0085334",
          "rank": "67",
          "rankUpDown": "+34",
          "title": "A Christmas Story",
          "fullTitle": "A Christmas Story (1983)",
          "year": "1983",
          "image": "https://m.media-amazon.com/images/M/MV5BOWMyNjE0MzEtMzVjNy00NjIxLTg0ZjMtMWJhNGI1YmVjYTczL2ltYWdlXkEyXkFqcGdeQXVyNzc5MjA3OA@@._V1_UX128_CR0,3,128,176_AL_.jpg",
          "crew": "Bob Clark (dir.), Peter Billingsley, Melinda Dillon",
          "imDbRating": "7.9",
          "imDbRatingCount": "129286"
      },
      {
          "id": "tt9340860",
          "rank": "68",
          "rankUpDown": "-39",
          "title": "Let Him Go",
          "fullTitle": "Let Him Go (2020)",
          "year": "2020",
          "image": "https://m.media-amazon.com/images/M/MV5BNGNhN2I2NzEtMzFiMy00Y2IzLTk0OTctNjcxZmYwYjIyMzEzXkEyXkFqcGdeQXVyNjY1MTg4Mzc@._V1_UX128_CR0,3,128,176_AL_.jpg",
          "crew": "Thomas Bezucha (dir.), Diane Lane, Kevin Costner",
          "imDbRating": "6.7",
          "imDbRatingCount": "6271"
      },
      {
          "id": "tt10838180",
          "rank": "69",
          "rankUpDown": "-22",
          "title": "The Matrix 4",
          "fullTitle": "The Matrix 4 (2021)",
          "year": "2021",
          "image": "https://m.media-amazon.com/images/M/MV5BN2I5NzlmMWYtYjIwYy00Y2ZiLWI0ODgtYjAxNDZiZGJlMjlhXkEyXkFqcGdeQXVyMzk1MDQ2MQ@@._V1_UY176_CR69,0,128,176_AL_.jpg",
          "crew": "Lana Wachowski (dir.), Keanu Reeves, Jonathan Groff",
          "imDbRating": "",
          "imDbRatingCount": "0"
      },
      {
          "id": "tt9252468",
          "rank": "70",
          "rankUpDown": "-59",
          "title": "Mosul",
          "fullTitle": "Mosul (2019)",
          "year": "2019",
          "image": "https://m.media-amazon.com/images/M/MV5BYWU1MzZkOGQtMTE2ZS00YmMzLTkzMzctMTc0ZjU1NDFlOWZkXkEyXkFqcGdeQXVyODk4OTc3MTY@._V1_UX128_CR0,1,128,176_AL_.jpg",
          "crew": "Matthew Michael Carnahan (dir.), Waleed Elgadi, Hayat Kamille",
          "imDbRating": "7.2",
          "imDbRatingCount": "15692"
      },
      {
          "id": "tt6456326",
          "rank": "71",
          "rankUpDown": "+717",
          "title": "Monsters of Man",
          "fullTitle": "Monsters of Man (2020)",
          "year": "2020",
          "image": "https://m.media-amazon.com/images/M/MV5BMDlkYzRmODAtZjczMy00ODdjLWE4MDUtMzA5YmYwNTVlMTEyXkEyXkFqcGdeQXVyNDQ0MDAxNQ@@._V1_UX128_CR0,3,128,176_AL_.jpg",
          "crew": "Mark Toia (dir.), Neal McDonough, Brett Tutor",
          "imDbRating": "5.1",
          "imDbRatingCount": "1258"
      },
      {
          "id": "tt0241527",
          "rank": "72",
          "rankUpDown": "-13",
          "title": "Harry Potter and the Sorcerer's Stone",
          "fullTitle": "Harry Potter and the Sorcerer's Stone (2001)",
          "year": "2001",
          "image": "https://m.media-amazon.com/images/M/MV5BNjQ3NWNlNmQtMTE5ZS00MDdmLTlkZjUtZTBlM2UxMGFiMTU3XkEyXkFqcGdeQXVyNjUwNzk3NDc@._V1_UX128_CR0,3,128,176_AL_.jpg",
          "crew": "Chris Columbus (dir.), Daniel Radcliffe, Rupert Grint",
          "imDbRating": "7.6",
          "imDbRatingCount": "646594"
      },
      {
          "id": "tt1070874",
          "rank": "73",
          "rankUpDown": "-25",
          "title": "The Trial of the Chicago 7",
          "fullTitle": "The Trial of the Chicago 7 (2020)",
          "year": "2020",
          "image": "https://m.media-amazon.com/images/M/MV5BYjYzOGE1MjUtODgyMy00ZDAxLTljYTgtNzk0Njg2YWQwMTZhXkEyXkFqcGdeQXVyMDM2NDM2MQ@@._V1_UX128_CR0,3,128,176_AL_.jpg",
          "crew": "Aaron Sorkin (dir.), Eddie Redmayne, Alex Sharp",
          "imDbRating": "7.8",
          "imDbRatingCount": "69941"
      },
      {
          "id": "tt9620292",
          "rank": "74",
          "rankUpDown": "+154",
          "title": "Promising Young Woman",
          "fullTitle": "Promising Young Woman (2020)",
          "year": "2020",
          "image": "https://m.media-amazon.com/images/M/MV5BZDViMzBiNGMtZTIyNS00NzI4LWE3NDMtNmM1NDk0NzBlMWRlXkEyXkFqcGdeQXVyMTA2MDU0NjM5._V1_UX128_CR0,3,128,176_AL_.jpg",
          "crew": "Emerald Fennell (dir.), Carey Mulligan, Bo Burnham",
          "imDbRating": "6.3",
          "imDbRatingCount": "723"
      },
      {
          "id": "tt2527338",
          "rank": "75",
          "rankUpDown": "+12",
          "title": "Star Wars: Episode IX - The Rise of Skywalker",
          "fullTitle": "Star Wars: Episode IX - The Rise of Skywalker (2019)",
          "year": "2019",
          "image": "https://m.media-amazon.com/images/M/MV5BMDljNTQ5ODItZmQwMy00M2ExLTljOTQtZTVjNGE2NTg0NGIxXkEyXkFqcGdeQXVyODkzNTgxMDg@._V1_UX128_CR0,3,128,176_AL_.jpg",
          "crew": "J.J. Abrams (dir.), Daisy Ridley, John Boyega",
          "imDbRating": "6.6",
          "imDbRatingCount": "362329"
      },
      {
          "id": "tt4154796",
          "rank": "76",
          "rankUpDown": "-5",
          "title": "Avengers: Endgame",
          "fullTitle": "Avengers: Endgame (2019)",
          "year": "2019",
          "image": "https://m.media-amazon.com/images/M/MV5BMTc5MDE2ODcwNV5BMl5BanBnXkFtZTgwMzI2NzQ2NzM@._V1_UX128_CR0,3,128,176_AL_.jpg",
          "crew": "Anthony Russo (dir.), Robert Downey Jr., Chris Evans",
          "imDbRating": "8.4",
          "imDbRatingCount": "787545"
      },
      {
          "id": "tt3963816",
          "rank": "77",
          "rankUpDown": "+202",
          "title": "Marauders",
          "fullTitle": "Marauders (2016)",
          "year": "2016",
          "image": "https://m.media-amazon.com/images/M/MV5BODU2OTc1OTgyMF5BMl5BanBnXkFtZTgwOTU4OTMxOTE@._V1_UX128_CR0,3,128,176_AL_.jpg",
          "crew": "Steven C. Miller (dir.), Bruce Willis, Christopher Meloni",
          "imDbRating": "5.5",
          "imDbRatingCount": "19427"
      },
      {
          "id": "tt6842770",
          "rank": "78",
          "rankUpDown": "+592",
          "title": "Wild Mountain Thyme",
          "fullTitle": "Wild Mountain Thyme (2020)",
          "year": "2020",
          "image": "https://m.media-amazon.com/images/M/MV5BYzhhOTdiYzAtMDJiYS00NDA0LWJmN2EtODljMDJmNDMxZDk3XkEyXkFqcGdeQXVyMTEyMjM2NDc2._V1_UX128_CR0,3,128,176_AL_.jpg",
          "crew": "John Patrick Shanley (dir.), Emily Blunt, Jamie Dornan",
          "imDbRating": "5.5",
          "imDbRatingCount": "501"
      },
      {
          "id": "tt12592252",
          "rank": "79",
          "rankUpDown": "+514",
          "title": "Songbird",
          "fullTitle": "Songbird (2020)",
          "year": "2020",
          "image": "https://m.media-amazon.com/images/M/MV5BZDA1MTYxNjctYjQyOS00OTQ2LWFkNGMtMmZkNDg0ZDNjNDYyXkEyXkFqcGdeQXVyNjY1MTg4Mzc@._V1_UX128_CR0,3,128,176_AL_.jpg",
          "crew": "Adam Mason (dir.), K.J. Apa, Sofia Carson",
          "imDbRating": "4.3",
          "imDbRatingCount": "899"
      },
      {
          "id": "tt1375666",
          "rank": "80",
          "rankUpDown": "-45",
          "title": "Inception",
          "fullTitle": "Inception (2010)",
          "year": "2010",
          "image": "https://m.media-amazon.com/images/M/MV5BMjAxMzY3NjcxNF5BMl5BanBnXkFtZTcwNTI5OTM0Mw@@._V1_UX128_CR0,3,128,176_AL_.jpg",
          "crew": "Christopher Nolan (dir.), Leonardo DiCaprio, Joseph Gordon-Levitt",
          "imDbRating": "8.8",
          "imDbRatingCount": "2043442"
      },
      {
          "id": "tt0120737",
          "rank": "81",
          "rankUpDown": "+7",
          "title": "The Lord of the Rings: The Fellowship of the Ring",
          "fullTitle": "The Lord of the Rings: The Fellowship of the Ring (2001)",
          "year": "2001",
          "image": "https://m.media-amazon.com/images/M/MV5BN2EyZjM3NzUtNWUzMi00MTgxLWI0NTctMzY4M2VlOTdjZWRiXkEyXkFqcGdeQXVyNDUzOTQ5MjY@._V1_UX128_CR0,3,128,176_AL_.jpg",
          "crew": "Peter Jackson (dir.), Elijah Wood, Ian McKellen",
          "imDbRating": "8.8",
          "imDbRatingCount": "1643588"
      },
      {
          "id": "tt6334354",
          "rank": "82",
          "rankUpDown": "-17",
          "title": "The Suicide Squad",
          "fullTitle": "The Suicide Squad (2021)",
          "year": "2021",
          "image": "https://m.media-amazon.com/images/M/MV5BMzEzNzEyM2EtODM3OC00NWM4LTk3OTEtZjg3YjEzYTM1Zjk2XkEyXkFqcGdeQXVyMTkxNjUyNQ@@._V1_UX128_CR0,3,128,176_AL_.jpg",
          "crew": "James Gunn (dir.), Margot Robbie, Taika Waititi",
          "imDbRating": "",
          "imDbRatingCount": "0"
      },
      {
          "id": "tt10243992",
          "rank": "83",
          "rankUpDown": "+946",
          "title": "I'm Your Woman",
          "fullTitle": "I'm Your Woman (2020)",
          "year": "2020",
          "image": "https://m.media-amazon.com/images/M/MV5BOGZhZGM2MjQtODY0ZC00ZmRkLThjOGQtOTAwMGFkYTY5ZmZlXkEyXkFqcGdeQXVyMTEyMjM2NDc2._V1_UX128_CR0,3,128,176_AL_.jpg",
          "crew": "Julia Hart (dir.), Rachel Brosnahan, Marsha Stephanie Blake",
          "imDbRating": "6.1",
          "imDbRatingCount": "1259"
      },
      {
          "id": "tt2850386",
          "rank": "84",
          "rankUpDown": "-43",
          "title": "The Croods: A New Age",
          "fullTitle": "The Croods: A New Age (2020)",
          "year": "2020",
          "image": "https://m.media-amazon.com/images/M/MV5BNGE1NjMzMjAtNDJiNi00YjE1LWJmN2QtOGZmMmJhNmQ3OTBiXkEyXkFqcGdeQXVyMDM2NDM2MQ@@._V1_UX128_CR0,3,128,176_AL_.jpg",
          "crew": "Joel Crawford (dir.), Nicolas Cage, Emma Stone",
          "imDbRating": "7.1",
          "imDbRatingCount": "1417"
      },
      {
          "id": "tt5918982",
          "rank": "85",
          "rankUpDown": "+24",
          "title": "Possessor",
          "fullTitle": "Possessor (2020)",
          "year": "2020",
          "image": "https://m.media-amazon.com/images/M/MV5BMjBlYTlhMDctNTQ3ZC00MjM4LWIxNjctNDI4NjA3NDc3Yzc5XkEyXkFqcGdeQXVyMTEyMjM2NDc2._V1_UX128_CR0,3,128,176_AL_.jpg",
          "crew": "Brandon Cronenberg (dir.), Andrea Riseborough, Christopher Abbott",
          "imDbRating": "6.4",
          "imDbRatingCount": "10294"
      },
      {
          "id": "tt6751668",
          "rank": "86",
          "rankUpDown": "-13",
          "title": "Parasite",
          "fullTitle": "Parasite (2019)",
          "year": "2019",
          "image": "https://m.media-amazon.com/images/M/MV5BYWZjMjk3ZTItODQ2ZC00NTY5LWE0ZDYtZTI3MjcwN2Q5NTVkXkEyXkFqcGdeQXVyODk4OTc3MTY@._V1_UX128_CR0,3,128,176_AL_.jpg",
          "crew": "Bong Joon Ho (dir.), Song Kang-Ho, Sun-kyun Lee",
          "imDbRating": "8.6",
          "imDbRatingCount": "520543"
      },
      {
          "id": "tt7131622",
          "rank": "87",
          "rankUpDown": "-27",
          "title": "Once Upon a Time... In Hollywood",
          "fullTitle": "Once Upon a Time... In Hollywood (2019)",
          "year": "2019",
          "image": "https://m.media-amazon.com/images/M/MV5BOTg4ZTNkZmUtMzNlZi00YmFjLTk1MmUtNWQwNTM0YjcyNTNkXkEyXkFqcGdeQXVyNjg2NjQwMDQ@._V1_UX128_CR0,3,128,176_AL_.jpg",
          "crew": "Quentin Tarantino (dir.), Leonardo DiCaprio, Brad Pitt",
          "imDbRating": "7.6",
          "imDbRatingCount": "535415"
      },
      {
          "id": "tt0816692",
          "rank": "88",
          "rankUpDown": "-2",
          "title": "Interstellar",
          "fullTitle": "Interstellar (2014)",
          "year": "2014",
          "image": "https://m.media-amazon.com/images/M/MV5BZjdkOTU3MDktN2IxOS00OGEyLWFmMjktY2FiMmZkNWIyODZiXkEyXkFqcGdeQXVyMTMxODk2OTU@._V1_UX128_CR0,3,128,176_AL_.jpg",
          "crew": "Christopher Nolan (dir.), Matthew McConaughey, Anne Hathaway",
          "imDbRating": "8.6",
          "imDbRatingCount": "1488349"
      },
      {
          "id": "tt7888964",
          "rank": "89",
          "rankUpDown": "4,259",
          "title": "Nobody",
          "fullTitle": "Nobody (2021)",
          "year": "2021",
          "image": "https://m.media-amazon.com/images/M/MV5BY2EzNDUxNDAtYjQ4ZC00YmYwLWI3YTgtMzM0YzFhNjNiNjYzXkEyXkFqcGdeQXVyMTEyMjM2NDc2._V1_UX128_CR0,3,128,176_AL_.jpg",
          "crew": "Ilya Naishuller (dir.), Bob Odenkirk, Connie Nielsen",
          "imDbRating": "",
          "imDbRatingCount": "0"
      },
      {
          "id": "tt0107688",
          "rank": "90",
          "rankUpDown": "+8",
          "title": "The Nightmare Before Christmas",
          "fullTitle": "The Nightmare Before Christmas (1993)",
          "year": "1993",
          "image": "https://m.media-amazon.com/images/M/MV5BNWE4OTNiM2ItMjY4Ni00ZTViLWFiZmEtZGEyNGY2ZmNlMzIyXkEyXkFqcGdeQXVyMDU5NDcxNw@@._V1_UX128_CR0,3,128,176_AL_.jpg",
          "crew": "Henry Selick (dir.), Danny Elfman, Chris Sarandon",
          "imDbRating": "8.0",
          "imDbRatingCount": "296230"
      },
      {
          "id": "tt4633694",
          "rank": "91",
          "rankUpDown": "-40",
          "title": "Spider-Man: Into the Spider-Verse",
          "fullTitle": "Spider-Man: Into the Spider-Verse (2018)",
          "year": "2018",
          "image": "https://m.media-amazon.com/images/M/MV5BMjMwNDkxMTgzOF5BMl5BanBnXkFtZTgwNTkwNTQ3NjM@._V1_UX128_CR0,3,128,176_AL_.jpg",
          "crew": "Bob Persichetti (dir.), Shameik Moore, Jake Johnson",
          "imDbRating": "8.4",
          "imDbRatingCount": "362346"
      },
      {
          "id": "tt7395114",
          "rank": "92",
          "rankUpDown": "-36",
          "title": "The Devil All the Time",
          "fullTitle": "The Devil All the Time (2020)",
          "year": "2020",
          "image": "https://m.media-amazon.com/images/M/MV5BZmE1NmVmN2EtMjZmZC00YzAyLWE4MWEtYjY5YmExMjUxODU1XkEyXkFqcGdeQXVyMTkxNjUyNQ@@._V1_UX128_CR0,3,128,176_AL_.jpg",
          "crew": "Antonio Campos (dir.), Donald Ray Pollock, Bill Skarsgård",
          "imDbRating": "7.1",
          "imDbRatingCount": "80567"
      },
      {
          "id": "tt11286314",
          "rank": "93",
          "rankUpDown": "+23",
          "title": "Don't Look Up",
          "fullTitle": "Don't Look Up ( 23)",
          "year": " 23",
          "image": "https://m.media-amazon.com/images/M/MV5BZmUwNzcyYmMtYmU0ZC00MzllLTgzZDgtZTBlYTM2MjQ3NzE5XkEyXkFqcGdeQXVyMTE2NzA0Ng@@._V1_UY176_CR69,0,128,176_AL_.jpg",
          "crew": "Adam McKay (dir.), Leonardo DiCaprio, Meryl Streep",
          "imDbRating": "",
          "imDbRatingCount": "0"
      },
      {
          "id": "tt0293429",
          "rank": "94",
          "rankUpDown": "-49",
          "title": "Mortal Kombat",
          "fullTitle": "Mortal Kombat (2021)",
          "year": "2021",
          "image": "https://m.media-amazon.com/images/M/MV5BY2VkZTcxM2QtMTYyNi00YzA5LTlmMWMtNDYzOTIxMzQ2MjczXkEyXkFqcGdeQXVyMTkxNjUyNQ@@._V1_UX128_CR0,3,128,176_AL_.jpg",
          "crew": "Simon McQuoid (dir.), Jessica McNamee, Hiroyuki Sanada",
          "imDbRating": "",
          "imDbRatingCount": "0"
      },
      {
          "id": "tt0111161",
          "rank": "95",
          "rankUpDown": "-4",
          "title": "The Shawshank Redemption",
          "fullTitle": "The Shawshank Redemption (1994)",
          "year": "1994",
          "image": "https://m.media-amazon.com/images/M/MV5BMDFkYTc0MGEtZmNhMC00ZDIzLWFmNTEtODM1ZmRlYWMwMWFmXkEyXkFqcGdeQXVyMTMxODk2OTU@._V1_UX128_CR0,3,128,176_AL_.jpg",
          "crew": "Frank Darabont (dir.), Tim Robbins, Morgan Freeman",
          "imDbRating": "9.3",
          "imDbRatingCount": "2318006"
      },
      {
          "id": "tt7846844",
          "rank": "96",
          "rankUpDown": "-32",
          "title": "Enola Holmes",
          "fullTitle": "Enola Holmes (2020)",
          "year": "2020",
          "image": "https://m.media-amazon.com/images/M/MV5BZjNkNzk0ZjEtM2M1ZC00MmMxLTlmOWEtNWRlZTc1ZTUyNzY4XkEyXkFqcGdeQXVyMTEyMjM2NDc2._V1_UX128_CR0,3,128,176_AL_.jpg",
          "crew": "Harry Bradbeer (dir.), Millie Bobby Brown, Henry Cavill",
          "imDbRating": "6.6",
          "imDbRatingCount": "111806"
      },
      {
          "id": "tt7286456",
          "rank": "97",
          "rankUpDown": "-13",
          "title": "Joker",
          "fullTitle": "Joker (2019)",
          "year": "2019",
          "image": "https://m.media-amazon.com/images/M/MV5BNGVjNWI4ZGUtNzE0MS00YTJmLWE0ZDctN2ZiYTk2YmI3NTYyXkEyXkFqcGdeQXVyMTkxNjUyNQ@@._V1_UX128_CR0,3,128,176_AL_.jpg",
          "crew": "Todd Phillips (dir.), Joaquin Phoenix, Robert De Niro",
          "imDbRating": "8.5",
          "imDbRatingCount": "909305"
      },
      {
          "id": "tt3748528",
          "rank": "98",
          "rankUpDown": "+61",
          "title": "Rogue One: A Star Wars Story",
          "fullTitle": "Rogue One: A Star Wars Story (2016)",
          "year": "2016",
          "image": "https://m.media-amazon.com/images/M/MV5BMjEwMzMxODIzOV5BMl5BanBnXkFtZTgwNzg3OTAzMDI@._V1_UX128_CR0,3,128,176_AL_.jpg",
          "crew": "Gareth Edwards (dir.), Felicity Jones, Diego Luna",
          "imDbRating": "7.8",
          "imDbRatingCount": "548049"
      },
      {
          "id": "tt10059518",
          "rank": "99",
          "rankUpDown": "-27",
          "title": "Unhinged",
          "fullTitle": "Unhinged (2020)",
          "year": "2020",
          "image": "https://m.media-amazon.com/images/M/MV5BYjc1Mjg5NjItY2I2MS00NDk3LWI5NGYtNzZjNTNiZmMwZTA3XkEyXkFqcGdeQXVyMjM4NTM5NDY@._V1_UX128_CR0,3,128,176_AL_.jpg",
          "crew": "Derrick Borte (dir.), Russell Crowe, Caren Pistorius",
          "imDbRating": "6.0",
          "imDbRatingCount": "26337"
      },
      {
          "id": "tt1712261",
          "rank": "100",
          "rankUpDown": "2,276",
          "title": "Triple 9",
          "fullTitle": "Triple 9 (2016)",
          "year": "2016",
          "image": "https://m.media-amazon.com/images/M/MV5BMjQyMjg2NDk0MV5BMl5BanBnXkFtZTgwNzU5Njc5NjE@._V1_UX128_CR0,3,128,176_AL_.jpg",
          "crew": "John Hillcoat (dir.), Casey Affleck, Chiwetel Ejiofor",
          "imDbRating": "6.3",
          "imDbRatingCount": "65535"
      }
  ],
  "errorMessage": ""
}